autodmri/__init__.py
autodmri/blocks.py
autodmri/estimator.py
autodmri/gamma.py
autodmri/scripts.py
autodmri-0.2.7.dist-info/LICENSE
autodmri-0.2.7.dist-info/METADATA
autodmri-0.2.7.dist-info/WHEEL
autodmri-0.2.7.dist-info/entry_points.txt
autodmri-0.2.7.dist-info/top_level.txt
autodmri-0.2.7.dist-info/RECORD
