Metadata-Version: 2.1
Name: autodmri
Version: 0.2.7
Summary: Implementation of "Automated characterization of noise distributions in diffusion MRI data".
Author: Samuel St-Jean
License: MIT
Project-URL: homepage, https://github.com/samuelstjean/autodmri
Project-URL: documentation, https://autodmri.readthedocs.io/en/latest/
Project-URL: changelog, https://github.com/samuelstjean/autodmri/blob/master/CHANGELOG.md
Requires-Python: >=3.7
License-File: LICENSE
Requires-Dist: numpy >=1.15
Requires-Dist: scipy >=1.0
Requires-Dist: tqdm >=4.56
Requires-Dist: joblib >=0.12
Requires-Dist: nibabel >=2.4
